[
  {
    "condition": "location_check",
    "offsetX": -1,
    "offsetZ": 0,
    "offsetY": 0,
    "predicate": {
      "block": {
        "blocks": [
          "minecraft:hopper"
        ],
        "state": {
          "enabled": true
        }
      }
    }
  },
  {
    "condition": "location_check",
    "offsetX": -1,
    "offsetZ": 1,
    "offsetY": 0,
    "predicate": {
      "block": {
        "blocks": [
          "minecraft:hopper"
        ],
        "state": {
          "facing": "north"
        }
      }
    }
  },
  {
    "condition": "location_check",
    "offsetX": -1,
    "offsetZ": -1,
    "offsetY": 0,
    "predicate": {
      "block": {
        "blocks": [
          "minecraft:hopper"
        ],
        "state": {
          "facing": "south"
        }
      }
    }
  },
  {
    "condition": "location_check",
    "offsetX": -1,
    "offsetZ": 1,
    "offsetY": 1,
    "predicate": {
      "fluid": {
        "fluid": "minecraft:water"
      }
    }
  },
  {
    "condition": "location_check",
    "offsetX": -1,
    "offsetZ": -1,
    "offsetY": 1,
    "predicate": {
      "fluid": {
        "fluid": "minecraft:lava"
      }
    }
  }
]
